air_benchmark/__init__.py
air_benchmark/air_benchmark.py
air_benchmark/console.py
air_benchmark/evaluation_utils/__init__.py
air_benchmark/evaluation_utils/data_loader.py
air_benchmark/evaluation_utils/evaluation_arguments.py
air_benchmark/evaluation_utils/evaluator.py
air_benchmark/evaluation_utils/searcher.py
air_benchmark/evaluation_utils/utils.py
air_benchmark/tasks/__init__.py
air_benchmark/tasks/tasks.py
air_benchmark/tasks/v24_04/long_doc_tasks.py
air_benchmark/tasks/v24_04/qa_tasks.py
air_benchmark/tasks/v24_04/tasks.py
air_benchmark/tasks/v24_05/long_doc_tasks.py
air_benchmark/tasks/v24_05/qa_tasks.py
air_benchmark/tasks/v24_05/tasks.py
examples/evaluate_jina_model.py
examples/evaluate_openai_embedding.py
scripts/eval_dev_results.py
scripts/zip_results.py
scripts/bm25/evaluate_bm25.py
scripts/bm25/utils/__init__.py
scripts/bm25/utils/arguments.py
scripts/bm25/utils/models.py
scripts/bm25/utils/searcher.py
scripts/hf-transformers/evaluate_hf_transformers.py
scripts/hf-transformers/utils/__init__.py
scripts/hf-transformers/utils/arguments.py
scripts/hf-transformers/utils/models.py
scripts/hf-transformers/utils/searcher.py
scripts/sentence-transformers/evaluate_sentence_transformers.py
scripts/sentence-transformers/utils/__init__.py
scripts/sentence-transformers/utils/arguments.py
scripts/sentence-transformers/utils/models.py
scripts/sentence-transformers/utils/searcher.py
air_benchmark-0.1.0.dist-info/LICENSE
air_benchmark-0.1.0.dist-info/METADATA
air_benchmark-0.1.0.dist-info/WHEEL
air_benchmark-0.1.0.dist-info/entry_points.txt
air_benchmark-0.1.0.dist-info/top_level.txt
air_benchmark-0.1.0.dist-info/RECORD
