Metadata-Version: 2.1
Name: air-benchmark
Version: 0.1.0
Summary: AIR-Bench: Automated Heterogeneous Information Retrieval Benchmark
Author-email: BAAI <zhengliu1026@gmail.com>, Jina AI <research@jina.ai>
License: MIT License
Project-URL: homepage, https://github.com/AIR-Bench/AIR-Bench/tree/main
Project-URL: Huggingface Organization, https://huggingface.co/AIR-Bench
Project-URL: Leaderboard, https://huggingface.co/spaces/AIR-Bench/leaderboard
Keywords: embedding,benchmark,air-bench,reranker,information retrieval
Classifier: Development Status :: 4 - Beta
Classifier: Environment :: Console
Classifier: Intended Audience :: Developers
Classifier: Intended Audience :: Information Technology
Classifier: License :: OSI Approved :: MIT License
Classifier: Operating System :: OS Independent
Classifier: Programming Language :: Python
Requires-Python: >=3.8
License-File: LICENSE
Requires-Dist: datasets>=2.19.0
Requires-Dist: rich>=13.7.1
Requires-Dist: pytrec-eval
Provides-Extra: dev
Requires-Dist: black; extra == "dev"
Requires-Dist: isort; extra == "dev"
Requires-Dist: pytest; extra == "dev"
